bellu_love/__init__.py
bellu_love/ascii_art.py
bellu_love/love_calculator.py
bellu_love/messages.py
bellu_love/romantic_utils.py
bellu_love-1.0.4.dist-info/METADATA
bellu_love-1.0.4.dist-info/WHEEL
bellu_love-1.0.4.dist-info/RECORD
