Metadata-Version: 2.4
Name: bellu-love
Version: 1.0.4
Summary: A romantic Python library dedicated to Bellu - filled with love, poems, and sweet messages
Author-email: BITANU <mbitanu.evolve@gmail.com>
License: MIT
Keywords: bellu,love,messages,poetry,romantic
Requires-Python: >=3.8
